djaa_list_filter2/__init__.py
djaa_list_filter2/admin.py
djaa_list_filter2/apps.py
djaa_list_filter2/static/djaa_list_filter2/admin/css/autocomplete_list_filter.css
djaa_list_filter2/static/djaa_list_filter2/admin/js/autocomplete_list_filter.js
djaa_list_filter2/templates/djaa_list_filter2/admin/filter/autocomplete_list_filter.html
django_admin_autocomplete_list_filter2-1.0.3.dist-info/licenses/LICENCE
django_admin_autocomplete_list_filter2-1.0.3.dist-info/METADATA
django_admin_autocomplete_list_filter2-1.0.3.dist-info/WHEEL
django_admin_autocomplete_list_filter2-1.0.3.dist-info/top_level.txt
django_admin_autocomplete_list_filter2-1.0.3.dist-info/RECORD
